moprofiler/__init__.py
moprofiler/base.py
moprofiler/memory.py
moprofiler/stopwatch.py
moprofiler/time.py
moprofiler-1.1.0.dist-info/LICENSE
moprofiler-1.1.0.dist-info/METADATA
moprofiler-1.1.0.dist-info/WHEEL
moprofiler-1.1.0.dist-info/top_level.txt
moprofiler-1.1.0.dist-info/RECORD
