Metadata-Version: 2.1
Name: moprofiler
Version: 1.1.0
Summary: 综合性能分析工具，集成了内存使用、执行时间的分析器，及秒表打点工具
Home-page: https://github.com/littlemo/moprofiler
Author: littlemo
Author-email: moore@moorehy.com
Maintainer: littlemo
Maintainer-email: moore@moorehy.com
License: GPLv3
Project-URL: Source, https://github.com/littlemo/moprofiler
Project-URL: Documentation, http://moprofiler.rtfd.io/
Project-URL: Tracker, https://github.com/littlemo/moprofiler/issues
Keywords: moprofiler profiler tool memory time
Platform: UNKNOWN
Classifier: Development Status :: 4 - Beta
Classifier: Environment :: Console
Classifier: Environment :: MacOS X
Classifier: Intended Audience :: Developers
Classifier: License :: OSI Approved :: GNU General Public License v3 (GPLv3)
Classifier: Natural Language :: Chinese (Simplified)
Classifier: Operating System :: MacOS
Classifier: Operating System :: POSIX :: Linux
Classifier: Programming Language :: Python
Classifier: Programming Language :: Python :: 2
Classifier: Programming Language :: Python :: 2.7
Classifier: Programming Language :: Python :: 3
Classifier: Programming Language :: Python :: 3.5
Classifier: Topic :: Communications :: Email
Classifier: Topic :: Documentation :: Sphinx
Classifier: Topic :: Software Development :: Testing :: Unit
Classifier: Topic :: Software Development :: Libraries :: Python Modules
Classifier: Topic :: Software Development :: User Interfaces
Classifier: Topic :: Software Development :: Version Control :: Git
Classifier: Topic :: Terminals
Classifier: Topic :: Text Editors :: Emacs
Classifier: Topic :: Utilities
Requires-Python: >=2.7
Requires-Dist: line-profiler (>=2.1.2)
Requires-Dist: memory-profiler (>=0.55.0)
Requires-Dist: pyaop (~=0.0.6)
